ntnx_backupclient_sdk/__init__.py
ntnx_backupclient_sdk/client.py
nutanix_backup_client_sdk-0.1.1.dist-info/METADATA
nutanix_backup_client_sdk-0.1.1.dist-info/WHEEL
nutanix_backup_client_sdk-0.1.1.dist-info/top_level.txt
nutanix_backup_client_sdk-0.1.1.dist-info/RECORD
